rocketparser/RocketParser.pyd
rocketparser/__init__.py
rocketparser-1.1.4.dist-info/LICENSE.txt
rocketparser-1.1.4.dist-info/METADATA
rocketparser-1.1.4.dist-info/WHEEL
rocketparser-1.1.4.dist-info/top_level.txt
rocketparser-1.1.4.dist-info/RECORD
