Metadata-Version: 2.1
Name: rocketparser
Version: 1.1.4
Summary: Parses rocketrecorder files
Home-page: http://rocketrecorder.com
Author: GodGamer029
License: UNKNOWN
Project-URL: Website, http://rocketrecorder.com
Keywords: rocketrecorder machine learning parser flatbuffer rocket-league
Platform: UNKNOWN
Classifier: Development Status :: 4 - Beta
Classifier: Intended Audience :: Developers
Classifier: Topic :: Scientific/Engineering :: Artificial Intelligence
Classifier: License :: OSI Approved :: MIT License
Classifier: Operating System :: Microsoft :: Windows
Classifier: Programming Language :: Python :: 3
Classifier: Programming Language :: Python :: 3.5
Classifier: Programming Language :: Python :: 3.6
Classifier: Programming Language :: Python :: 3.7
Classifier: Programming Language :: Python :: 3.8
Requires-Python: >=3.5, <4
Requires-Dist: numpy
